[{"register_no":"22MB087","device_name":"104","date_time":"2024-01-19T08:46:39+05:30","period":1,"timetable":25},{"register_no":"22MB138","device_name":"104","date_time":"2024-01-19T08:46:54+05:30","period":1,"timetable":25},{"register_no":"22MB138","device_name":"104","date_time":"2024-01-19T08:46:55+05:30","period":1,"timetable":25},{"register_no":"22MB031","device_name":"104","date_time":"2024-01-19T08:47:25+05:30","period":1,"timetable":25},{"register_no":"22MB030","device_name":"104","date_time":"2024-01-19T08:47:28+05:30","period":1,"timetable":25},{"register_no":"22MB070","device_name":"104","date_time":"2024-01-19T08:47:30+05:30","period":1,"timetable":25},{"register_no":"22MB025","device_name":"104","date_time":"2024-01-19T08:49:03+05:30","period":1,"timetable":25},{"register_no":"22MB009","device_name":"104","date_time":"2024-01-19T08:49:07+05:30","period":1,"timetable":25},{"register_no":"22MB009","device_name":"104","date_time":"2024-01-19T08:49:07+05:30","period":1,"timetable":25},{"register_no":"22MB102","device_name":"104","date_time":"2024-01-19T08:51:00+05:30","period":1,"timetable":25},{"register_no":"22MB102","device_name":"104","date_time":"2024-01-19T08:51:02+05:30","period":1,"timetable":25},{"register_no":"22MB017","device_name":"104","date_time":"2024-01-19T08:51:04+05:30","period":1,"timetable":25},{"register_no":"22MB007","device_name":"104","date_time":"2024-01-19T08:51:10+05:30","period":1,"timetable":25},{"register_no":"22MB088","device_name":"104","date_time":"2024-01-19T08:52:25+05:30","period":1,"timetable":25},{"register_no":"22MB027","device_name":"104","date_time":"2024-01-19T08:52:27+05:30","period":1,"timetable":25},{"register_no":"22MB117","device_name":"104","date_time":"2024-01-19T08:55:36+05:30","period":1,"timetable":25},{"register_no":"22MB104","device_name":"104","date_time":"2024-01-19T08:56:41+05:30","period":1,"timetable":25},{"register_no":"22MB071","device_name":"104","date_time":"2024-01-19T08:59:21+05:30","period":1,"timetable":25},{"register_no":"22MB021","device_name":"104","date_time":"2024-01-19T08:59:22+05:30","period":1,"timetable":25},{"register_no":"22MB128","device_name":"104","date_time":"2024-01-19T09:02:23+05:30","period":1,"timetable":25},{"register_no":"22MB097","device_name":"104","date_time":"2024-01-19T09:02:55+05:30","period":1,"timetable":25},{"register_no":"22MB097","device_name":"104","date_time":"2024-01-19T09:02:57+05:30","period":1,"timetable":25},{"register_no":"22MB097","device_name":"104","date_time":"2024-01-19T09:02:58+05:30","period":1,"timetable":25},{"register_no":"22MB067","device_name":"104","date_time":"2024-01-19T09:03:00+05:30","period":1,"timetable":25},{"register_no":"22MB067","device_name":"104","date_time":"2024-01-19T09:03:00+05:30","period":1,"timetable":25},{"register_no":"22MB091","device_name":"104","date_time":"2024-01-19T09:03:02+05:30","period":1,"timetable":25},{"register_no":"22MB109","device_name":"104","date_time":"2024-01-19T09:04:16+05:30","period":1,"timetable":25},{"register_no":"22MB033","device_name":"104","date_time":"2024-01-19T09:04:41+05:30","period":1,"timetable":25},{"register_no":"22MB087","device_name":"104","date_time":"2024-01-19T09:04:44+05:30","period":1,"timetable":25},{"register_no":"22MB004","device_name":"104","date_time":"2024-01-19T09:04:46+05:30","period":1,"timetable":25},{"register_no":"22MB004","device_name":"104","date_time":"2024-01-19T09:04:46+05:30","period":1,"timetable":25},{"register_no":"22MB127","device_name":"104","date_time":"2024-01-19T09:07:19+05:30","period":1,"timetable":25},{"register_no":"22MB127","device_name":"104","date_time":"2024-01-19T09:07:19+05:30","period":1,"timetable":25},{"register_no":"22MB141","device_name":"104","date_time":"2024-01-19T09:14:29+05:30","period":1,"timetable":25},{"register_no":"22MB132","device_name":"104","date_time":"2024-01-19T09:14:33+05:30","period":1,"timetable":25}]