[{"register_no":"20MB085","device_name":"106","date_time":"2024-10-03T13:08:24+05:30","period":4,"timetable":120},{"register_no":"20MB069","device_name":"106","date_time":"2024-10-03T13:08:27+05:30","period":4,"timetable":120},{"register_no":"20MB069","device_name":"106","date_time":"2024-10-03T13:08:28+05:30","period":4,"timetable":120},{"register_no":"20MB076","device_name":"106","date_time":"2024-10-03T13:10:02+05:30","period":4,"timetable":120},{"register_no":"20MB015","device_name":"106","date_time":"2024-10-03T13:10:05+05:30","period":4,"timetable":120},{"register_no":"20MB045","device_name":"106","date_time":"2024-10-03T13:10:40+05:30","period":4,"timetable":120},{"register_no":"20MB001","device_name":"106","date_time":"2024-10-03T13:10:41+05:30","period":4,"timetable":120},{"register_no":"20MB086","device_name":"106","date_time":"2024-10-03T13:10:52+05:30","period":4,"timetable":120},{"register_no":"20MB090","device_name":"106","date_time":"2024-10-03T13:11:08+05:30","period":4,"timetable":120},{"register_no":"20MB099","device_name":"106","date_time":"2024-10-03T13:11:12+05:30","period":4,"timetable":120},{"register_no":"20MB082","device_name":"106","date_time":"2024-10-03T13:11:28+05:30","period":4,"timetable":120},{"register_no":"20MB026","device_name":"106","date_time":"2024-10-03T13:11:31+05:30","period":4,"timetable":120},{"register_no":"20MB053","device_name":"106","date_time":"2024-10-03T13:11:33+05:30","period":4,"timetable":120},{"register_no":"20MB114","device_name":"106","date_time":"2024-10-03T13:12:11+05:30","period":4,"timetable":120},{"register_no":"20MB017","device_name":"106","date_time":"2024-10-03T13:12:14+05:30","period":4,"timetable":120},{"register_no":"20MB042","device_name":"106","date_time":"2024-10-03T13:12:23+05:30","period":4,"timetable":120},{"register_no":"20MB071","device_name":"106","date_time":"2024-10-03T13:12:37+05:30","period":4,"timetable":120},{"register_no":"20MB043","device_name":"106","date_time":"2024-10-03T13:12:58+05:30","period":4,"timetable":120},{"register_no":"20MB059","device_name":"106","date_time":"2024-10-03T13:14:32+05:30","period":4,"timetable":120},{"register_no":"20MB096","device_name":"106","date_time":"2024-10-03T13:15:30+05:30","period":4,"timetable":120},{"register_no":"20MB007","device_name":"106","date_time":"2024-10-03T13:15:31+05:30","period":4,"timetable":120},{"register_no":"20MB021","device_name":"106","date_time":"2024-10-03T13:15:35+05:30","period":4,"timetable":120},{"register_no":"20MB033","device_name":"106","date_time":"2024-10-03T13:15:39+05:30","period":4,"timetable":120},{"register_no":"20MB135","device_name":"106","date_time":"2024-10-03T13:17:25+05:30","period":4,"timetable":120},{"register_no":"20MB077","device_name":"106","date_time":"2024-10-03T13:18:45+05:30","period":4,"timetable":120},{"register_no":"20MB116","device_name":"106","date_time":"2024-10-03T13:19:15+05:30","period":4,"timetable":120},{"register_no":"20MB116","device_name":"106","date_time":"2024-10-03T13:19:16+05:30","period":4,"timetable":120},{"register_no":"20MB074","device_name":"106","date_time":"2024-10-03T13:19:18+05:30","period":4,"timetable":120},{"register_no":"20MB005","device_name":"106","date_time":"2024-10-03T13:20:34+05:30","period":4,"timetable":120},{"register_no":"20MB119","device_name":"106","date_time":"2024-10-03T13:21:48+05:30","period":4,"timetable":120},{"register_no":"20MB013","device_name":"106","date_time":"2024-10-03T13:26:31+05:30","period":4,"timetable":120},{"register_no":"20MB013","device_name":"106","date_time":"2024-10-03T13:26:32+05:30","period":4,"timetable":120},{"register_no":"20MB044","device_name":"106","date_time":"2024-10-03T13:26:34+05:30","period":4,"timetable":120},{"register_no":"20MB109","device_name":"106","date_time":"2024-10-03T13:28:54+05:30","period":4,"timetable":120},{"register_no":"20MB137","device_name":"106","date_time":"2024-10-03T13:29:22+05:30","period":4,"timetable":120},{"register_no":"20MB079","device_name":"106","date_time":"2024-10-03T13:29:25+05:30","period":4,"timetable":120},{"register_no":"20MB014","device_name":"106","date_time":"2024-10-03T13:34:13+05:30","period":4,"timetable":120},{"register_no":"20MB025","device_name":"106","date_time":"2024-10-03T13:34:16+05:30","period":4,"timetable":120},{"register_no":"20MB102","device_name":"106","date_time":"2024-10-03T13:34:19+05:30","period":4,"timetable":120},{"register_no":"20MB107","device_name":"106","date_time":"2024-10-03T13:34:22+05:30","period":4,"timetable":120},{"register_no":"20MB012","device_name":"106","date_time":"2024-10-03T13:35:50+05:30","period":4,"timetable":120},{"register_no":"20MB019","device_name":"106","date_time":"2024-10-03T13:35:53+05:30","period":4,"timetable":120},{"register_no":"20MB093","device_name":"106","date_time":"2024-10-03T13:42:59+05:30","period":4,"timetable":120},{"register_no":"20MB097","device_name":"106","date_time":"2024-10-03T13:43:02+05:30","period":4,"timetable":120}]