[{"register_no":"21MB141","device_name":"108","date_time":"2025-03-13T13:05:44+05:30","period":4,"timetable":88},{"register_no":"21MB130","device_name":"108","date_time":"2025-03-13T13:05:51+05:30","period":4,"timetable":88},{"register_no":"21MB006","device_name":"108","date_time":"2025-03-13T13:06:46+05:30","period":4,"timetable":88},{"register_no":"21MB035","device_name":"108","date_time":"2025-03-13T13:06:49+05:30","period":4,"timetable":88},{"register_no":"21MB035","device_name":"108","date_time":"2025-03-13T13:06:49+05:30","period":4,"timetable":88},{"register_no":"21MB030","device_name":"108","date_time":"2025-03-13T13:06:58+05:30","period":4,"timetable":88},{"register_no":"21MB090","device_name":"108","date_time":"2025-03-13T13:07:24+05:30","period":4,"timetable":88},{"register_no":"21MB133","device_name":"108","date_time":"2025-03-13T13:07:41+05:30","period":4,"timetable":88},{"register_no":"21MB133","device_name":"108","date_time":"2025-03-13T13:07:42+05:30","period":4,"timetable":88},{"register_no":"21MB119","device_name":"108","date_time":"2025-03-13T13:08:48+05:30","period":4,"timetable":88},{"register_no":"21MB119","device_name":"108","date_time":"2025-03-13T13:08:51+05:30","period":4,"timetable":88},{"register_no":"21MB063","device_name":"108","date_time":"2025-03-13T13:08:55+05:30","period":4,"timetable":88},{"register_no":"21MB063","device_name":"108","date_time":"2025-03-13T13:08:55+05:30","period":4,"timetable":88},{"register_no":"21MB124","device_name":"108","date_time":"2025-03-13T13:08:57+05:30","period":4,"timetable":88},{"register_no":"21MB089","device_name":"108","date_time":"2025-03-13T13:09:04+05:30","period":4,"timetable":88},{"register_no":"21MB019","device_name":"108","date_time":"2025-03-13T13:09:10+05:30","period":4,"timetable":88},{"register_no":"21MB011","device_name":"108","date_time":"2025-03-13T13:09:13+05:30","period":4,"timetable":88},{"register_no":"21MB131","device_name":"108","date_time":"2025-03-13T13:10:28+05:30","period":4,"timetable":88},{"register_no":"21MB028","device_name":"108","date_time":"2025-03-13T13:10:31+05:30","period":4,"timetable":88},{"register_no":"21MB054","device_name":"108","date_time":"2025-03-13T13:11:37+05:30","period":4,"timetable":88},{"register_no":"21MB057","device_name":"108","date_time":"2025-03-13T13:11:40+05:30","period":4,"timetable":88},{"register_no":"21MB009","device_name":"108","date_time":"2025-03-13T13:11:43+05:30","period":4,"timetable":88},{"register_no":"21MB142","device_name":"108","date_time":"2025-03-13T13:11:46+05:30","period":4,"timetable":88},{"register_no":"21MB003","device_name":"108","date_time":"2025-03-13T13:11:47+05:30","period":4,"timetable":88},{"register_no":"21MB032","device_name":"108","date_time":"2025-03-13T13:12:05+05:30","period":4,"timetable":88},{"register_no":"21MB040","device_name":"108","date_time":"2025-03-13T13:12:07+05:30","period":4,"timetable":88},{"register_no":"21MB044","device_name":"108","date_time":"2025-03-13T13:12:21+05:30","period":4,"timetable":88},{"register_no":"21MB080","device_name":"108","date_time":"2025-03-13T13:12:24+05:30","period":4,"timetable":88},{"register_no":"21MB075","device_name":"108","date_time":"2025-03-13T13:15:18+05:30","period":4,"timetable":88},{"register_no":"21MB004","device_name":"108","date_time":"2025-03-13T13:15:34+05:30","period":4,"timetable":88},{"register_no":"21MB049","device_name":"108","date_time":"2025-03-13T13:15:36+05:30","period":4,"timetable":88},{"register_no":"21MB029","device_name":"108","date_time":"2025-03-13T13:23:01+05:30","period":4,"timetable":88},{"register_no":"21MB072","device_name":"108","date_time":"2025-03-13T13:23:03+05:30","period":4,"timetable":88},{"register_no":"21MB072","device_name":"108","date_time":"2025-03-13T13:23:04+05:30","period":4,"timetable":88}]