[{"register_no":"20MB077","device_name":"106","date_time":"2024-08-16T09:53:54+05:30","period":2,"timetable":143},{"register_no":"20MB127","device_name":"106","date_time":"2024-08-16T09:54:01+05:30","period":2,"timetable":143},{"register_no":"20MB082","device_name":"106","date_time":"2024-08-16T09:54:57+05:30","period":2,"timetable":143},{"register_no":"20MB116","device_name":"106","date_time":"2024-08-16T09:55:02+05:30","period":2,"timetable":143},{"register_no":"20MB065","device_name":"106","date_time":"2024-08-16T09:55:07+05:30","period":2,"timetable":143},{"register_no":"20MB026","device_name":"106","date_time":"2024-08-16T09:55:10+05:30","period":2,"timetable":143},{"register_no":"20MB085","device_name":"106","date_time":"2024-08-16T09:55:12+05:30","period":2,"timetable":143},{"register_no":"20MB053","device_name":"106","date_time":"2024-08-16T09:55:14+05:30","period":2,"timetable":143},{"register_no":"20MB093","device_name":"106","date_time":"2024-08-16T09:55:19+05:30","period":2,"timetable":143},{"register_no":"20MB119","device_name":"106","date_time":"2024-08-16T09:55:22+05:30","period":2,"timetable":143},{"register_no":"20MB074","device_name":"106","date_time":"2024-08-16T09:55:29+05:30","period":2,"timetable":143},{"register_no":"20MB074","device_name":"106","date_time":"2024-08-16T09:55:30+05:30","period":2,"timetable":143},{"register_no":"20MB017","device_name":"106","date_time":"2024-08-16T09:55:39+05:30","period":2,"timetable":143},{"register_no":"20MB123","device_name":"106","date_time":"2024-08-16T09:55:44+05:30","period":2,"timetable":143},{"register_no":"20MB068","device_name":"106","date_time":"2024-08-16T09:55:48+05:30","period":2,"timetable":143},{"register_no":"20MB114","device_name":"106","date_time":"2024-08-16T09:55:51+05:30","period":2,"timetable":143},{"register_no":"20MB073","device_name":"106","date_time":"2024-08-16T09:55:55+05:30","period":2,"timetable":143},{"register_no":"20MB030","device_name":"106","date_time":"2024-08-16T09:58:05+05:30","period":2,"timetable":143},{"register_no":"20MB030","device_name":"106","date_time":"2024-08-16T09:58:05+05:30","period":2,"timetable":143},{"register_no":"20MB037","device_name":"106","date_time":"2024-08-16T09:58:46+05:30","period":2,"timetable":143},{"register_no":"20MB003","device_name":"106","date_time":"2024-08-16T09:59:11+05:30","period":2,"timetable":143},{"register_no":"20MB027","device_name":"106","date_time":"2024-08-16T09:59:26+05:30","period":2,"timetable":143},{"register_no":"20MB002","device_name":"106","date_time":"2024-08-16T10:01:32+05:30","period":2,"timetable":143},{"register_no":"20MB022","device_name":"106","date_time":"2024-08-16T10:06:35+05:30","period":2,"timetable":143},{"register_no":"20MB043","device_name":"106","date_time":"2024-08-16T10:09:14+05:30","period":2,"timetable":143},{"register_no":"20MB014","device_name":"106","date_time":"2024-08-16T10:10:20+05:30","period":2,"timetable":143},{"register_no":"20MB141","device_name":"106","date_time":"2024-08-16T10:10:30+05:30","period":2,"timetable":143},{"register_no":"20MB141","device_name":"106","date_time":"2024-08-16T10:10:30+05:30","period":2,"timetable":143},{"register_no":"20MB143","device_name":"106","date_time":"2024-08-16T10:10:42+05:30","period":2,"timetable":143},{"register_no":"20MB025","device_name":"106","date_time":"2024-08-16T10:11:09+05:30","period":2,"timetable":143},{"register_no":"20MB142","device_name":"106","date_time":"2024-08-16T10:11:21+05:30","period":2,"timetable":143},{"register_no":"20MB142","device_name":"106","date_time":"2024-08-16T10:11:21+05:30","period":2,"timetable":143},{"register_no":"20MB083","device_name":"106","date_time":"2024-08-16T10:12:16+05:30","period":2,"timetable":143},{"register_no":"20MB086","device_name":"106","date_time":"2024-08-16T10:13:16+05:30","period":2,"timetable":143},{"register_no":"20MB086","device_name":"106","date_time":"2024-08-16T10:13:16+05:30","period":2,"timetable":143},{"register_no":"20MB112","device_name":"106","date_time":"2024-08-16T10:13:19+05:30","period":2,"timetable":143},{"register_no":"20MB090","device_name":"106","date_time":"2024-08-16T10:14:29+05:30","period":2,"timetable":143},{"register_no":"20MB090","device_name":"106","date_time":"2024-08-16T10:14:29+05:30","period":2,"timetable":143},{"register_no":"20MB047","device_name":"106","date_time":"2024-08-16T10:20:30+05:30","period":2,"timetable":143},{"register_no":"20MB134","device_name":"106","date_time":"2024-08-16T11:05:25+05:30","period":2,"timetable":143},{"register_no":"20MB100","device_name":"106","date_time":"2024-08-16T11:19:09+05:30","period":2,"timetable":143},{"register_no":"20MB090","device_name":"106","date_time":"2024-08-16T12:12:01+05:30","period":2,"timetable":143},{"register_no":"20MB143","device_name":"106","date_time":"2024-08-16T12:17:12+05:30","period":2,"timetable":143}]