[{"register_no":"20MB018","device_name":"106","date_time":"2024-02-28T12:28:02+05:30","period":3,"timetable":114},{"register_no":"20MB150","device_name":"106","date_time":"2024-02-28T12:31:24+05:30","period":3,"timetable":114},{"register_no":"20MB110","device_name":"106","date_time":"2024-02-28T12:31:27+05:30","period":3,"timetable":114},{"register_no":"20MB058","device_name":"106","date_time":"2024-02-28T12:44:48+05:30","period":3,"timetable":114},{"register_no":"20MB058","device_name":"106","date_time":"2024-02-28T12:44:48+05:30","period":3,"timetable":114},{"register_no":"20MB054","device_name":"106","date_time":"2024-02-28T12:44:49+05:30","period":3,"timetable":114},{"register_no":"20MB054","device_name":"106","date_time":"2024-02-28T12:44:50+05:30","period":3,"timetable":114},{"register_no":"20MB043","device_name":"106","date_time":"2024-02-28T12:50:54+05:30","period":3,"timetable":114},{"register_no":"20MB030","device_name":"106","date_time":"2024-02-28T12:53:00+05:30","period":3,"timetable":114},{"register_no":"20MB150","device_name":"106","date_time":"2024-02-28T12:57:18+05:30","period":3,"timetable":114},{"register_no":"20MB053","device_name":"106","date_time":"2024-02-28T12:59:24+05:30","period":3,"timetable":114},{"register_no":"20MB053","device_name":"106","date_time":"2024-02-28T12:59:24+05:30","period":3,"timetable":114},{"register_no":"20MB071","device_name":"106","date_time":"2024-02-28T12:59:26+05:30","period":3,"timetable":114},{"register_no":"20MB027","device_name":"106","date_time":"2024-02-28T13:00:42+05:30","period":3,"timetable":114},{"register_no":"20MB125","device_name":"106","date_time":"2024-02-28T13:01:04+05:30","period":3,"timetable":114},{"register_no":"20MB125","device_name":"106","date_time":"2024-02-28T13:01:05+05:30","period":3,"timetable":114},{"register_no":"20MB026","device_name":"106","date_time":"2024-02-28T13:01:11+05:30","period":3,"timetable":114},{"register_no":"19MB023","device_name":"106","date_time":"2024-02-28T13:01:28+05:30","period":3,"timetable":114},{"register_no":"19MB076","device_name":"106","date_time":"2024-02-28T13:01:32+05:30","period":3,"timetable":114},{"register_no":"20MB073","device_name":"106","date_time":"2024-02-28T13:02:14+05:30","period":3,"timetable":114},{"register_no":"20MB089","device_name":"106","date_time":"2024-02-28T13:02:40+05:30","period":3,"timetable":114},{"register_no":"20MB119","device_name":"106","date_time":"2024-02-28T13:03:09+05:30","period":3,"timetable":114},{"register_no":"20MB123","device_name":"106","date_time":"2024-02-28T13:03:12+05:30","period":3,"timetable":114},{"register_no":"20MB077","device_name":"106","date_time":"2024-02-28T13:03:15+05:30","period":3,"timetable":114},{"register_no":"20MB142","device_name":"106","date_time":"2024-02-28T13:03:28+05:30","period":3,"timetable":114},{"register_no":"20MB142","device_name":"106","date_time":"2024-02-28T13:03:29+05:30","period":3,"timetable":114},{"register_no":"20MB143","device_name":"106","date_time":"2024-02-28T13:03:30+05:30","period":3,"timetable":114}]