[{"register_no":"21MB115","device_name":"108","date_time":"2024-09-25T13:08:52+05:30","period":4,"timetable":82},{"register_no":"21MB005","device_name":"108","date_time":"2024-09-25T13:08:57+05:30","period":4,"timetable":82},{"register_no":"21MB042","device_name":"108","date_time":"2024-09-25T13:09:46+05:30","period":4,"timetable":82},{"register_no":"21MB042","device_name":"108","date_time":"2024-09-25T13:09:46+05:30","period":4,"timetable":82},{"register_no":"21MB052","device_name":"108","date_time":"2024-09-25T13:09:48+05:30","period":4,"timetable":82},{"register_no":"21MB012","device_name":"108","date_time":"2024-09-25T13:10:00+05:30","period":4,"timetable":82},{"register_no":"21MB071","device_name":"108","date_time":"2024-09-25T13:10:04+05:30","period":4,"timetable":82},{"register_no":"21MB081","device_name":"108","date_time":"2024-09-25T13:10:08+05:30","period":4,"timetable":82},{"register_no":"21MB080","device_name":"108","date_time":"2024-09-25T13:11:59+05:30","period":4,"timetable":82},{"register_no":"21MB028","device_name":"108","date_time":"2024-09-25T13:12:05+05:30","period":4,"timetable":82},{"register_no":"21MB096","device_name":"108","date_time":"2024-09-25T13:13:05+05:30","period":4,"timetable":82},{"register_no":"21MB120","device_name":"108","date_time":"2024-09-25T13:17:56+05:30","period":4,"timetable":82},{"register_no":"20MB031","device_name":"108","date_time":"2024-09-25T13:17:58+05:30","period":4,"timetable":82},{"register_no":"21MB040","device_name":"108","date_time":"2024-09-25T13:21:06+05:30","period":4,"timetable":82},{"register_no":"21MB029","device_name":"108","date_time":"2024-09-25T13:22:51+05:30","period":4,"timetable":82},{"register_no":"21MB049","device_name":"108","date_time":"2024-09-25T13:30:16+05:30","period":4,"timetable":82}]