[{"register_no":"21MB017","device_name":"106","date_time":"2025-05-03T08:34:34+05:30","period":1,"timetable":97},{"register_no":"21MB017","device_name":"106","date_time":"2025-05-03T08:34:35+05:30","period":1,"timetable":97},{"register_no":"21MB061","device_name":"106","date_time":"2025-05-03T08:34:39+05:30","period":1,"timetable":97},{"register_no":"21MB115","device_name":"106","date_time":"2025-05-03T08:35:33+05:30","period":1,"timetable":97},{"register_no":"21MB115","device_name":"106","date_time":"2025-05-03T08:35:33+05:30","period":1,"timetable":97},{"register_no":"21MB023","device_name":"106","date_time":"2025-05-03T08:42:45+05:30","period":1,"timetable":97},{"register_no":"21MB135","device_name":"106","date_time":"2025-05-03T08:44:03+05:30","period":1,"timetable":97},{"register_no":"21MB128","device_name":"106","date_time":"2025-05-03T08:44:41+05:30","period":1,"timetable":97},{"register_no":"21MB007","device_name":"106","date_time":"2025-05-03T08:44:44+05:30","period":1,"timetable":97},{"register_no":"21MB100","device_name":"106","date_time":"2025-05-03T08:44:53+05:30","period":1,"timetable":97},{"register_no":"21MB100","device_name":"106","date_time":"2025-05-03T08:45:34+05:30","period":1,"timetable":97},{"register_no":"21MB020","device_name":"106","date_time":"2025-05-03T08:46:09+05:30","period":1,"timetable":97},{"register_no":"21MB020","device_name":"106","date_time":"2025-05-03T08:46:10+05:30","period":1,"timetable":97},{"register_no":"21MB011","device_name":"106","date_time":"2025-05-03T08:46:13+05:30","period":1,"timetable":97},{"register_no":"21MB002","device_name":"106","date_time":"2025-05-03T08:47:16+05:30","period":1,"timetable":97},{"register_no":"20MB131","device_name":"106","date_time":"2025-05-03T08:47:23+05:30","period":1,"timetable":97},{"register_no":"21MB107","device_name":"106","date_time":"2025-05-03T08:48:18+05:30","period":1,"timetable":97},{"register_no":"21MB107","device_name":"106","date_time":"2025-05-03T08:48:19+05:30","period":1,"timetable":97},{"register_no":"21MB092","device_name":"106","date_time":"2025-05-03T08:48:59+05:30","period":1,"timetable":97},{"register_no":"21MB039","device_name":"106","date_time":"2025-05-03T08:49:15+05:30","period":1,"timetable":97},{"register_no":"21MB016","device_name":"106","date_time":"2025-05-03T08:49:16+05:30","period":1,"timetable":97},{"register_no":"21MB045","device_name":"106","date_time":"2025-05-03T08:49:24+05:30","period":1,"timetable":97},{"register_no":"21MB044","device_name":"106","date_time":"2025-05-03T08:49:27+05:30","period":1,"timetable":97},{"register_no":"20MB036","device_name":"106","date_time":"2025-05-03T08:50:02+05:30","period":1,"timetable":97},{"register_no":"20MB036","device_name":"106","date_time":"2025-05-03T08:50:05+05:30","period":1,"timetable":97},{"register_no":"20MB070","device_name":"106","date_time":"2025-05-03T08:50:08+05:30","period":1,"timetable":97},{"register_no":"21MB131","device_name":"106","date_time":"2025-05-03T08:50:13+05:30","period":1,"timetable":97},{"register_no":"21MB093","device_name":"106","date_time":"2025-05-03T08:50:34+05:30","period":1,"timetable":97},{"register_no":"21MB013","device_name":"106","date_time":"2025-05-03T08:50:37+05:30","period":1,"timetable":97},{"register_no":"21MB013","device_name":"106","date_time":"2025-05-03T08:50:37+05:30","period":1,"timetable":97},{"register_no":"21MB138","device_name":"106","date_time":"2025-05-03T08:50:38+05:30","period":1,"timetable":97},{"register_no":"21MB056","device_name":"106","date_time":"2025-05-03T08:50:43+05:30","period":1,"timetable":97},{"register_no":"21MB056","device_name":"106","date_time":"2025-05-03T08:50:44+05:30","period":1,"timetable":97},{"register_no":"21MB068","device_name":"106","date_time":"2025-05-03T08:50:46+05:30","period":1,"timetable":97},{"register_no":"21MB068","device_name":"106","date_time":"2025-05-03T08:50:47+05:30","period":1,"timetable":97},{"register_no":"21MB006","device_name":"106","date_time":"2025-05-03T08:50:56+05:30","period":1,"timetable":97},{"register_no":"21MB035","device_name":"106","date_time":"2025-05-03T08:50:58+05:30","period":1,"timetable":97},{"register_no":"21MB099","device_name":"106","date_time":"2025-05-03T08:51:10+05:30","period":1,"timetable":97},{"register_no":"21MB025","device_name":"106","date_time":"2025-05-03T08:51:58+05:30","period":1,"timetable":97},{"register_no":"21MB025","device_name":"106","date_time":"2025-05-03T08:51:59+05:30","period":1,"timetable":97},{"register_no":"20MB122","device_name":"106","date_time":"2025-05-03T08:52:27+05:30","period":1,"timetable":97},{"register_no":"21MB129","device_name":"106","date_time":"2025-05-03T08:52:32+05:30","period":1,"timetable":97},{"register_no":"21MB054","device_name":"106","date_time":"2025-05-03T08:52:37+05:30","period":1,"timetable":97},{"register_no":"21MB080","device_name":"106","date_time":"2025-05-03T08:52:39+05:30","period":1,"timetable":97},{"register_no":"21MB142","device_name":"106","date_time":"2025-05-03T08:52:42+05:30","period":1,"timetable":97},{"register_no":"21MB079","device_name":"106","date_time":"2025-05-03T08:52:43+05:30","period":1,"timetable":97},{"register_no":"21MB036","device_name":"106","date_time":"2025-05-03T08:52:45+05:30","period":1,"timetable":97},{"register_no":"20MB031","device_name":"106","date_time":"2025-05-03T08:52:51+05:30","period":1,"timetable":97},{"register_no":"21MB060","device_name":"106","date_time":"2025-05-03T08:53:03+05:30","period":1,"timetable":97},{"register_no":"21MB147","device_name":"106","date_time":"2025-05-03T08:53:06+05:30","period":1,"timetable":97},{"register_no":"21MB033","device_name":"106","date_time":"2025-05-03T08:53:09+05:30","period":1,"timetable":97},{"register_no":"21MB104","device_name":"106","date_time":"2025-05-03T08:53:38+05:30","period":1,"timetable":97},{"register_no":"21MB098","device_name":"106","date_time":"2025-05-03T08:53:59+05:30","period":1,"timetable":97},{"register_no":"21MB098","device_name":"106","date_time":"2025-05-03T08:54:00+05:30","period":1,"timetable":97},{"register_no":"21MB133","device_name":"106","date_time":"2025-05-03T08:54:04+05:30","period":1,"timetable":97},{"register_no":"21MB029","device_name":"106","date_time":"2025-05-03T08:54:19+05:30","period":1,"timetable":97},{"register_no":"21MB078","device_name":"106","date_time":"2025-05-03T08:54:22+05:30","period":1,"timetable":97},{"register_no":"21MB010","device_name":"106","date_time":"2025-05-03T08:54:22+05:30","period":1,"timetable":97},{"register_no":"21MB078","device_name":"106","date_time":"2025-05-03T08:54:26+05:30","period":1,"timetable":97},{"register_no":"21MB005","device_name":"106","date_time":"2025-05-03T08:54:29+05:30","period":1,"timetable":97},{"register_no":"20MB131","device_name":"106","date_time":"2025-05-03T08:54:29+05:30","period":1,"timetable":97},{"register_no":"21MB097","device_name":"106","date_time":"2025-05-03T08:54:43+05:30","period":1,"timetable":97},{"register_no":"21MB148","device_name":"106","date_time":"2025-05-03T08:54:45+05:30","period":1,"timetable":97},{"register_no":"21MB102","device_name":"106","date_time":"2025-05-03T08:54:47+05:30","period":1,"timetable":97},{"register_no":"21MB141","device_name":"106","date_time":"2025-05-03T08:54:50+05:30","period":1,"timetable":97},{"register_no":"21MB083","device_name":"106","date_time":"2025-05-03T08:55:11+05:30","period":1,"timetable":97},{"register_no":"21MB030","device_name":"106","date_time":"2025-05-03T08:55:14+05:30","period":1,"timetable":97},{"register_no":"21MB130","device_name":"106","date_time":"2025-05-03T08:55:16+05:30","period":1,"timetable":97},{"register_no":"21MB126","device_name":"106","date_time":"2025-05-03T08:55:18+05:30","period":1,"timetable":97},{"register_no":"21MB149","device_name":"106","date_time":"2025-05-03T08:55:20+05:30","period":1,"timetable":97},{"register_no":"21MB087","device_name":"106","date_time":"2025-05-03T08:55:21+05:30","period":1,"timetable":97},{"register_no":"21MB119","device_name":"106","date_time":"2025-05-03T08:55:23+05:30","period":1,"timetable":97},{"register_no":"21MB014","device_name":"106","date_time":"2025-05-03T08:55:58+05:30","period":1,"timetable":97},{"register_no":"21MB120","device_name":"106","date_time":"2025-05-03T08:56:17+05:30","period":1,"timetable":97},{"register_no":"21MB112","device_name":"106","date_time":"2025-05-03T08:56:35+05:30","period":1,"timetable":97},{"register_no":"21MB112","device_name":"106","date_time":"2025-05-03T08:56:36+05:30","period":1,"timetable":97},{"register_no":"21MB123","device_name":"106","date_time":"2025-05-03T08:56:38+05:30","period":1,"timetable":97},{"register_no":"21MB123","device_name":"106","date_time":"2025-05-03T08:56:39+05:30","period":1,"timetable":97},{"register_no":"21MB140","device_name":"106","date_time":"2025-05-03T08:56:40+05:30","period":1,"timetable":97},{"register_no":"21MB004","device_name":"106","date_time":"2025-05-03T08:56:47+05:30","period":1,"timetable":97},{"register_no":"21MB003","device_name":"106","date_time":"2025-05-03T08:56:48+05:30","period":1,"timetable":97},{"register_no":"21MB069","device_name":"106","date_time":"2025-05-03T08:56:50+05:30","period":1,"timetable":97},{"register_no":"21MB069","device_name":"106","date_time":"2025-05-03T08:56:50+05:30","period":1,"timetable":97},{"register_no":"21MB057","device_name":"106","date_time":"2025-05-03T08:56:52+05:30","period":1,"timetable":97},{"register_no":"21MB075","device_name":"106","date_time":"2025-05-03T08:57:10+05:30","period":1,"timetable":97},{"register_no":"21MB124","device_name":"106","date_time":"2025-05-03T08:57:30+05:30","period":1,"timetable":97},{"register_no":"21MB124","device_name":"106","date_time":"2025-05-03T08:57:30+05:30","period":1,"timetable":97},{"register_no":"21MB028","device_name":"106","date_time":"2025-05-03T08:57:48+05:30","period":1,"timetable":97},{"register_no":"21MB012","device_name":"106","date_time":"2025-05-03T08:58:14+05:30","period":1,"timetable":97},{"register_no":"21MB106","device_name":"106","date_time":"2025-05-03T08:58:21+05:30","period":1,"timetable":97},{"register_no":"21MB150","device_name":"106","date_time":"2025-05-03T08:58:24+05:30","period":1,"timetable":97},{"register_no":"21MB150","device_name":"106","date_time":"2025-05-03T08:58:24+05:30","period":1,"timetable":97},{"register_no":"21MB110","device_name":"106","date_time":"2025-05-03T08:58:27+05:30","period":1,"timetable":97},{"register_no":"21MB022","device_name":"106","date_time":"2025-05-03T08:58:35+05:30","period":1,"timetable":97},{"register_no":"21MB127","device_name":"106","date_time":"2025-05-03T08:58:38+05:30","period":1,"timetable":97},{"register_no":"20MB034","device_name":"106","date_time":"2025-05-03T08:58:58+05:30","period":1,"timetable":97},{"register_no":"21MB065","device_name":"106","date_time":"2025-05-03T08:59:03+05:30","period":1,"timetable":97},{"register_no":"20MB121","device_name":"106","date_time":"2025-05-03T08:59:19+05:30","period":1,"timetable":97},{"register_no":"20MB121","device_name":"106","date_time":"2025-05-03T08:59:20+05:30","period":1,"timetable":97},{"register_no":"21MB084","device_name":"106","date_time":"2025-05-03T08:59:31+05:30","period":1,"timetable":97},{"register_no":"21MB040","device_name":"106","date_time":"2025-05-03T08:59:57+05:30","period":1,"timetable":97},{"register_no":"21MB032","device_name":"106","date_time":"2025-05-03T09:00:00+05:30","period":1,"timetable":97},{"register_no":"21MB117","device_name":"106","date_time":"2025-05-03T09:00:06+05:30","period":1,"timetable":97},{"register_no":"21MB001","device_name":"106","date_time":"2025-05-03T09:00:08+05:30","period":1,"timetable":97},{"register_no":"21MB111","device_name":"106","date_time":"2025-05-03T09:00:09+05:30","period":1,"timetable":97},{"register_no":"21MB037","device_name":"106","date_time":"2025-05-03T09:00:14+05:30","period":1,"timetable":97},{"register_no":"21MB042","device_name":"106","date_time":"2025-05-03T09:00:16+05:30","period":1,"timetable":97},{"register_no":"20MB088","device_name":"106","date_time":"2025-05-03T09:00:18+05:30","period":1,"timetable":97},{"register_no":"21MB074","device_name":"106","date_time":"2025-05-03T09:00:21+05:30","period":1,"timetable":97},{"register_no":"21MB090","device_name":"106","date_time":"2025-05-03T09:00:22+05:30","period":1,"timetable":97},{"register_no":"21MB144","device_name":"106","date_time":"2025-05-03T09:01:17+05:30","period":1,"timetable":97},{"register_no":"21MB143","device_name":"106","date_time":"2025-05-03T09:04:55+05:30","period":1,"timetable":97},{"register_no":"21MB070","device_name":"106","date_time":"2025-05-03T09:07:28+05:30","period":1,"timetable":97},{"register_no":"20MB066","device_name":"106","date_time":"2025-05-03T09:11:25+05:30","period":1,"timetable":97},{"register_no":"20MB066","device_name":"106","date_time":"2025-05-03T09:44:55+05:30","period":1,"timetable":97},{"register_no":"21MB102","device_name":"106","date_time":"2025-05-03T09:45:41+05:30","period":1,"timetable":97},{"register_no":"21MB097","device_name":"106","date_time":"2025-05-03T09:45:42+05:30","period":1,"timetable":97},{"register_no":"21MB097","device_name":"106","date_time":"2025-05-03T09:45:43+05:30","period":1,"timetable":97},{"register_no":"21MB128","device_name":"106","date_time":"2025-05-03T09:45:50+05:30","period":1,"timetable":97},{"register_no":"21MB049","device_name":"106","date_time":"2025-05-03T09:46:02+05:30","period":1,"timetable":97},{"register_no":"21MB049","device_name":"106","date_time":"2025-05-03T09:46:02+05:30","period":1,"timetable":97},{"register_no":"21MB049","device_name":"106","date_time":"2025-05-03T09:47:03+05:30","period":1,"timetable":97},{"register_no":"21MB141","device_name":"106","date_time":"2025-05-03T09:47:06+05:30","period":1,"timetable":97},{"register_no":"21MB070","device_name":"106","date_time":"2025-05-03T09:48:07+05:30","period":1,"timetable":97},{"register_no":"21MB046","device_name":"106","date_time":"2025-05-03T09:48:47+05:30","period":1,"timetable":97},{"register_no":"21MB069","device_name":"106","date_time":"2025-05-03T09:48:51+05:30","period":1,"timetable":97},{"register_no":"21MB069","device_name":"106","date_time":"2025-05-03T09:48:52+05:30","period":1,"timetable":97}]