[{"register_no":"20MB066","device_name":"103","date_time":"2023-11-03T14:29:50+05:30","period":5,"timetable":61},{"register_no":"21MB026","device_name":"103","date_time":"2023-11-03T14:30:16+05:30","period":5,"timetable":61},{"register_no":"21MB029","device_name":"103","date_time":"2023-11-03T14:30:18+05:30","period":5,"timetable":61},{"register_no":"21MB075","device_name":"103","date_time":"2023-11-03T14:30:20+05:30","period":5,"timetable":61},{"register_no":"21MB017","device_name":"103","date_time":"2023-11-03T14:30:25+05:30","period":5,"timetable":61},{"register_no":"21MB031","device_name":"103","date_time":"2023-11-03T14:30:28+05:30","period":5,"timetable":61},{"register_no":"21MB070","device_name":"103","date_time":"2023-11-03T14:30:35+05:30","period":5,"timetable":61},{"register_no":"21MB070","device_name":"103","date_time":"2023-11-03T14:30:36+05:30","period":5,"timetable":61},{"register_no":"21MB121","device_name":"103","date_time":"2023-11-03T14:30:38+05:30","period":5,"timetable":61},{"register_no":"21MB102","device_name":"103","date_time":"2023-11-03T14:30:41+05:30","period":5,"timetable":61},{"register_no":"21MB022","device_name":"103","date_time":"2023-11-03T14:30:50+05:30","period":5,"timetable":61},{"register_no":"21MB022","device_name":"103","date_time":"2023-11-03T14:30:50+05:30","period":5,"timetable":61},{"register_no":"21MB057","device_name":"103","date_time":"2023-11-03T14:31:00+05:30","period":5,"timetable":61},{"register_no":"21MB053","device_name":"103","date_time":"2023-11-03T14:31:03+05:30","period":5,"timetable":61},{"register_no":"21MB053","device_name":"103","date_time":"2023-11-03T14:31:04+05:30","period":5,"timetable":61},{"register_no":"21MB128","device_name":"103","date_time":"2023-11-03T14:31:07+05:30","period":5,"timetable":61},{"register_no":"21MB128","device_name":"103","date_time":"2023-11-03T14:31:07+05:30","period":5,"timetable":61},{"register_no":"21MB003","device_name":"103","date_time":"2023-11-03T14:31:12+05:30","period":5,"timetable":61},{"register_no":"21MB014","device_name":"103","date_time":"2023-11-03T14:31:16+05:30","period":5,"timetable":61},{"register_no":"21MB014","device_name":"103","date_time":"2023-11-03T14:31:16+05:30","period":5,"timetable":61},{"register_no":"21MB091","device_name":"103","date_time":"2023-11-03T14:31:18+05:30","period":5,"timetable":61},{"register_no":"21MB103","device_name":"103","date_time":"2023-11-03T14:31:20+05:30","period":5,"timetable":61},{"register_no":"21MB006","device_name":"103","date_time":"2023-11-03T14:31:24+05:30","period":5,"timetable":61},{"register_no":"20MB122","device_name":"103","date_time":"2023-11-03T14:32:13+05:30","period":5,"timetable":61},{"register_no":"20MB121","device_name":"103","date_time":"2023-11-03T14:32:17+05:30","period":5,"timetable":61},{"register_no":"20MB121","device_name":"103","date_time":"2023-11-03T14:32:17+05:30","period":5,"timetable":61}]