[{"register_no":"20MB051","device_name":"106","date_time":"2024-12-23T10:04:58+05:30","period":2,"timetable":139},{"register_no":"20MB048","device_name":"106","date_time":"2024-12-23T10:05:01+05:30","period":2,"timetable":139},{"register_no":"20MB085","device_name":"106","date_time":"2024-12-23T10:05:21+05:30","period":2,"timetable":139},{"register_no":"20MB116","device_name":"106","date_time":"2024-12-23T10:06:16+05:30","period":2,"timetable":139},{"register_no":"20MB133","device_name":"106","date_time":"2024-12-23T10:06:18+05:30","period":2,"timetable":139},{"register_no":"20MB093","device_name":"106","date_time":"2024-12-23T10:06:21+05:30","period":2,"timetable":139},{"register_no":"20MB074","device_name":"106","date_time":"2024-12-23T10:06:24+05:30","period":2,"timetable":139},{"register_no":"20MB114","device_name":"106","date_time":"2024-12-23T10:14:14+05:30","period":2,"timetable":139},{"register_no":"20MB110","device_name":"106","date_time":"2024-12-23T10:20:46+05:30","period":2,"timetable":139},{"register_no":"20MB014","device_name":"106","date_time":"2024-12-23T10:20:48+05:30","period":2,"timetable":139},{"register_no":"20MB040","device_name":"106","date_time":"2024-12-23T11:25:50+05:30","period":2,"timetable":139},{"register_no":"20MB007","device_name":"106","date_time":"2024-12-23T11:26:28+05:30","period":2,"timetable":139},{"register_no":"20MB030","device_name":"106","date_time":"2024-12-23T11:26:42+05:30","period":2,"timetable":139},{"register_no":"20MB116","device_name":"106","date_time":"2024-12-23T11:26:49+05:30","period":2,"timetable":139},{"register_no":"20MB116","device_name":"106","date_time":"2024-12-23T11:26:49+05:30","period":2,"timetable":139},{"register_no":"20MB133","device_name":"106","date_time":"2024-12-23T11:27:04+05:30","period":2,"timetable":139},{"register_no":"20MB133","device_name":"106","date_time":"2024-12-23T11:27:10+05:30","period":2,"timetable":139},{"register_no":"20MB133","device_name":"106","date_time":"2024-12-23T11:27:11+05:30","period":2,"timetable":139},{"register_no":"20MB091","device_name":"106","date_time":"2024-12-23T11:27:43+05:30","period":2,"timetable":139},{"register_no":"20MB091","device_name":"106","date_time":"2024-12-23T11:27:43+05:30","period":2,"timetable":139},{"register_no":"20MB100","device_name":"106","date_time":"2024-12-23T11:27:46+05:30","period":2,"timetable":139},{"register_no":"20MB135","device_name":"106","date_time":"2024-12-23T11:28:23+05:30","period":2,"timetable":139}]