[{"register_no":"21MB120","device_name":"102","date_time":"2023-10-20T14:11:51+05:30","period":5,"timetable":61},{"register_no":"21MB073","device_name":"102","date_time":"2023-10-20T14:13:27+05:30","period":5,"timetable":61},{"register_no":"21MB013","device_name":"102","date_time":"2023-10-20T14:13:30+05:30","period":5,"timetable":61},{"register_no":"21MB013","device_name":"102","date_time":"2023-10-20T14:13:30+05:30","period":5,"timetable":61},{"register_no":"21MB006","device_name":"102","date_time":"2023-10-20T14:13:32+05:30","period":5,"timetable":61},{"register_no":"21MB006","device_name":"102","date_time":"2023-10-20T14:13:33+05:30","period":5,"timetable":61},{"register_no":"21MB104","device_name":"102","date_time":"2023-10-20T14:13:46+05:30","period":5,"timetable":61},{"register_no":"21MB113","device_name":"102","date_time":"2023-10-20T14:14:51+05:30","period":5,"timetable":61},{"register_no":"20MB131","device_name":"102","date_time":"2023-10-20T14:14:54+05:30","period":5,"timetable":61},{"register_no":"21MB113","device_name":"102","date_time":"2023-10-20T14:14:57+05:30","period":5,"timetable":61},{"register_no":"20MB115","device_name":"102","date_time":"2023-10-20T14:15:04+05:30","period":5,"timetable":61},{"register_no":"20MB115","device_name":"102","date_time":"2023-10-20T14:15:05+05:30","period":5,"timetable":61},{"register_no":"21MB141","device_name":"102","date_time":"2023-10-20T14:15:19+05:30","period":5,"timetable":61},{"register_no":"21MB049","device_name":"102","date_time":"2023-10-20T14:15:25+05:30","period":5,"timetable":61},{"register_no":"21MB083","device_name":"102","date_time":"2023-10-20T14:15:27+05:30","period":5,"timetable":61},{"register_no":"21MB083","device_name":"102","date_time":"2023-10-20T14:15:28+05:30","period":5,"timetable":61},{"register_no":"21MB005","device_name":"102","date_time":"2023-10-20T14:15:31+05:30","period":5,"timetable":61},{"register_no":"21MB071","device_name":"102","date_time":"2023-10-20T14:15:32+05:30","period":5,"timetable":61},{"register_no":"21MB129","device_name":"102","date_time":"2023-10-20T14:15:35+05:30","period":5,"timetable":61},{"register_no":"21MB129","device_name":"102","date_time":"2023-10-20T14:15:36+05:30","period":5,"timetable":61},{"register_no":"21MB070","device_name":"102","date_time":"2023-10-20T14:15:37+05:30","period":5,"timetable":61},{"register_no":"21MB070","device_name":"102","date_time":"2023-10-20T14:15:38+05:30","period":5,"timetable":61},{"register_no":"21MB017","device_name":"102","date_time":"2023-10-20T14:15:40+05:30","period":5,"timetable":61},{"register_no":"21MB128","device_name":"102","date_time":"2023-10-20T14:15:43+05:30","period":5,"timetable":61},{"register_no":"21MB058","device_name":"102","date_time":"2023-10-20T14:15:45+05:30","period":5,"timetable":61},{"register_no":"21MB066","device_name":"102","date_time":"2023-10-20T14:15:48+05:30","period":5,"timetable":61},{"register_no":"21MB058","device_name":"102","date_time":"2023-10-20T14:15:49+05:30","period":5,"timetable":61},{"register_no":"21MB063","device_name":"102","date_time":"2023-10-20T14:15:52+05:30","period":5,"timetable":61},{"register_no":"21MB012","device_name":"102","date_time":"2023-10-20T14:15:55+05:30","period":5,"timetable":61},{"register_no":"21MB022","device_name":"102","date_time":"2023-10-20T14:15:56+05:30","period":5,"timetable":61},{"register_no":"21MB021","device_name":"102","date_time":"2023-10-20T14:15:59+05:30","period":5,"timetable":61},{"register_no":"21MB091","device_name":"102","date_time":"2023-10-20T14:16:01+05:30","period":5,"timetable":61},{"register_no":"21MB053","device_name":"102","date_time":"2023-10-20T14:16:02+05:30","period":5,"timetable":61},{"register_no":"21MB040","device_name":"102","date_time":"2023-10-20T14:16:05+05:30","period":5,"timetable":61},{"register_no":"21MB020","device_name":"102","date_time":"2023-10-20T14:16:06+05:30","period":5,"timetable":61},{"register_no":"21MB032","device_name":"102","date_time":"2023-10-20T14:16:09+05:30","period":5,"timetable":61},{"register_no":"21MB032","device_name":"102","date_time":"2023-10-20T14:16:09+05:30","period":5,"timetable":61},{"register_no":"21MB080","device_name":"102","date_time":"2023-10-20T14:16:12+05:30","period":5,"timetable":61},{"register_no":"21MB081","device_name":"102","date_time":"2023-10-20T14:16:15+05:30","period":5,"timetable":61},{"register_no":"21MB079","device_name":"102","date_time":"2023-10-20T14:16:15+05:30","period":5,"timetable":61},{"register_no":"21MB018","device_name":"102","date_time":"2023-10-20T14:16:19+05:30","period":5,"timetable":61},{"register_no":"21MB042","device_name":"102","date_time":"2023-10-20T14:16:22+05:30","period":5,"timetable":61},{"register_no":"21MB043","device_name":"102","date_time":"2023-10-20T14:16:26+05:30","period":5,"timetable":61},{"register_no":"21MB008","device_name":"102","date_time":"2023-10-20T14:16:28+05:30","period":5,"timetable":61},{"register_no":"21MB008","device_name":"102","date_time":"2023-10-20T14:16:28+05:30","period":5,"timetable":61},{"register_no":"21MB016","device_name":"102","date_time":"2023-10-20T14:16:31+05:30","period":5,"timetable":61},{"register_no":"21MB027","device_name":"102","date_time":"2023-10-20T14:16:33+05:30","period":5,"timetable":61},{"register_no":"21MB011","device_name":"102","date_time":"2023-10-20T14:16:35+05:30","period":5,"timetable":61},{"register_no":"21MB028","device_name":"102","date_time":"2023-10-20T14:16:38+05:30","period":5,"timetable":61},{"register_no":"21MB068","device_name":"102","date_time":"2023-10-20T14:16:41+05:30","period":5,"timetable":61},{"register_no":"21MB139","device_name":"102","date_time":"2023-10-20T14:16:43+05:30","period":5,"timetable":61},{"register_no":"21MB139","device_name":"102","date_time":"2023-10-20T14:16:43+05:30","period":5,"timetable":61},{"register_no":"21MB056","device_name":"102","date_time":"2023-10-20T14:16:45+05:30","period":5,"timetable":61},{"register_no":"21MB001","device_name":"102","date_time":"2023-10-20T14:16:47+05:30","period":5,"timetable":61},{"register_no":"21MB001","device_name":"102","date_time":"2023-10-20T14:16:47+05:30","period":5,"timetable":61},{"register_no":"21MB074","device_name":"102","date_time":"2023-10-20T14:16:51+05:30","period":5,"timetable":61},{"register_no":"21MB074","device_name":"102","date_time":"2023-10-20T14:16:52+05:30","period":5,"timetable":61},{"register_no":"21MB074","device_name":"102","date_time":"2023-10-20T14:16:53+05:30","period":5,"timetable":61},{"register_no":"21MB002","device_name":"102","date_time":"2023-10-20T14:16:55+05:30","period":5,"timetable":61},{"register_no":"21MB004","device_name":"102","date_time":"2023-10-20T14:16:58+05:30","period":5,"timetable":61},{"register_no":"21MB137","device_name":"102","date_time":"2023-10-20T14:18:34+05:30","period":5,"timetable":61}]