[{"register_no":"20MB150","device_name":"106","date_time":"2024-04-02T12:25:53+05:30","period":3,"timetable":109},{"register_no":"20MB136","device_name":"106","date_time":"2024-04-02T12:27:30+05:30","period":3,"timetable":109},{"register_no":"20MB145","device_name":"106","date_time":"2024-04-02T12:27:33+05:30","period":3,"timetable":109},{"register_no":"20MB142","device_name":"106","date_time":"2024-04-02T12:27:59+05:30","period":3,"timetable":109},{"register_no":"20MB143","device_name":"106","date_time":"2024-04-02T12:28:23+05:30","period":3,"timetable":109},{"register_no":"20MB111","device_name":"106","date_time":"2024-04-02T12:40:54+05:30","period":3,"timetable":109},{"register_no":"20MB014","device_name":"106","date_time":"2024-04-02T12:40:57+05:30","period":3,"timetable":109},{"register_no":"20MB046","device_name":"106","date_time":"2024-04-02T12:41:00+05:30","period":3,"timetable":109},{"register_no":"20MB117","device_name":"106","date_time":"2024-04-02T12:47:39+05:30","period":3,"timetable":109},{"register_no":"20MB071","device_name":"106","date_time":"2024-04-02T12:52:55+05:30","period":3,"timetable":109},{"register_no":"20MB004","device_name":"106","date_time":"2024-04-02T12:52:57+05:30","period":3,"timetable":109},{"register_no":"20MB135","device_name":"106","date_time":"2024-04-02T12:54:37+05:30","period":3,"timetable":109},{"register_no":"20MB137","device_name":"106","date_time":"2024-04-02T12:56:01+05:30","period":3,"timetable":109},{"register_no":"20MB079","device_name":"106","date_time":"2024-04-02T12:56:02+05:30","period":3,"timetable":109},{"register_no":"20MB058","device_name":"106","date_time":"2024-04-02T12:56:06+05:30","period":3,"timetable":109},{"register_no":"20MB128","device_name":"106","date_time":"2024-04-02T12:56:09+05:30","period":3,"timetable":109},{"register_no":"20MB077","device_name":"106","date_time":"2024-04-02T12:56:11+05:30","period":3,"timetable":109},{"register_no":"20MB013","device_name":"106","date_time":"2024-04-02T12:56:13+05:30","period":3,"timetable":109},{"register_no":"20MB013","device_name":"106","date_time":"2024-04-02T12:56:13+05:30","period":3,"timetable":109},{"register_no":"20MB027","device_name":"106","date_time":"2024-04-02T12:56:16+05:30","period":3,"timetable":109},{"register_no":"20MB027","device_name":"106","date_time":"2024-04-02T12:56:16+05:30","period":3,"timetable":109},{"register_no":"20MB123","device_name":"106","date_time":"2024-04-02T12:56:18+05:30","period":3,"timetable":109},{"register_no":"20MB037","device_name":"106","date_time":"2024-04-02T12:56:21+05:30","period":3,"timetable":109},{"register_no":"20MB028","device_name":"106","date_time":"2024-04-02T12:56:23+05:30","period":3,"timetable":109},{"register_no":"20MB001","device_name":"106","date_time":"2024-04-02T12:57:12+05:30","period":3,"timetable":109},{"register_no":"20MB001","device_name":"106","date_time":"2024-04-02T12:57:13+05:30","period":3,"timetable":109},{"register_no":"20MB015","device_name":"106","date_time":"2024-04-02T12:57:14+05:30","period":3,"timetable":109},{"register_no":"20MB047","device_name":"106","date_time":"2024-04-02T12:57:14+05:30","period":3,"timetable":109},{"register_no":"20MB045","device_name":"106","date_time":"2024-04-02T12:57:17+05:30","period":3,"timetable":109},{"register_no":"20MB055","device_name":"106","date_time":"2024-04-02T12:57:19+05:30","period":3,"timetable":109},{"register_no":"20MB076","device_name":"106","date_time":"2024-04-02T12:57:22+05:30","period":3,"timetable":109},{"register_no":"20MB129","device_name":"106","date_time":"2024-04-02T12:57:23+05:30","period":3,"timetable":109},{"register_no":"20MB043","device_name":"106","date_time":"2024-04-02T12:58:53+05:30","period":3,"timetable":109},{"register_no":"20MB043","device_name":"106","date_time":"2024-04-02T12:58:53+05:30","period":3,"timetable":109},{"register_no":"20MB006","device_name":"106","date_time":"2024-04-02T13:00:13+05:30","period":3,"timetable":109},{"register_no":"20MB006","device_name":"106","date_time":"2024-04-02T13:00:14+05:30","period":3,"timetable":109},{"register_no":"20MB110","device_name":"106","date_time":"2024-04-02T13:00:16+05:30","period":3,"timetable":109},{"register_no":"20MB005","device_name":"106","date_time":"2024-04-02T13:01:11+05:30","period":3,"timetable":109},{"register_no":"20MB127","device_name":"106","date_time":"2024-04-02T13:01:27+05:30","period":3,"timetable":109},{"register_no":"20MB044","device_name":"106","date_time":"2024-04-02T13:01:29+05:30","period":3,"timetable":109},{"register_no":"20MB085","device_name":"106","date_time":"2024-04-02T13:01:45+05:30","period":3,"timetable":109},{"register_no":"20MB125","device_name":"106","date_time":"2024-04-02T13:02:09+05:30","period":3,"timetable":109},{"register_no":"20MB017","device_name":"106","date_time":"2024-04-02T13:02:22+05:30","period":3,"timetable":109},{"register_no":"20MB016","device_name":"106","date_time":"2024-04-02T13:02:24+05:30","period":3,"timetable":109},{"register_no":"20MB074","device_name":"106","date_time":"2024-04-02T13:02:36+05:30","period":3,"timetable":109},{"register_no":"20MB116","device_name":"106","date_time":"2024-04-02T13:02:40+05:30","period":3,"timetable":109},{"register_no":"20MB074","device_name":"106","date_time":"2024-04-02T13:02:43+05:30","period":3,"timetable":109}]